{
  "schema_version": "2.0",
  "entries": [
    {
      "timestamp": "2026-05-06T20:23:07.583740+00:00",
      "branch": "feat/skill-scaffold-schemas",
      "summary": "Completed writing-style skill scaffold, artifact templates, conservative config defaults, and metadata alignment.",
      "decisions": "",
      "modules": []
    },
    {
      "timestamp": "2026-05-06T20:30:49.562825+00:00",
      "branch": "feat/core-skill-workflow",
      "summary": "Completed Writing Style workflow instructions, neutral calibration prompt bank, and feedback rubric.",
      "decisions": "",
      "modules": []
    },
    {
      "timestamp": "2026-05-06T21:09:10.379797+00:00",
      "branch": "feat/helper-scripts-tests",
      "summary": "Completed Writing Style helper scripts, fixtures, privacy scan, and unittest coverage.",
      "decisions": "",
      "modules": []
    }
  ]
}